{
  "model": "xgboost",
  "num_runs": 3,
  "inference_threshold": 0.105,
  "feature_dim": 22360,
  "dataset": {
    "trainval_webshell": 876,
    "trainval_benign": 4136,
    "fileless_test": 59
  },
  "runs": [
    {
      "run": 1,
      "seed": 42,
      "best_iteration": 37,
      "opt_threshold": 0.0847,
      "test": {
        "threshold": 0.5,
        "accuracy": 0.9947,
        "precision": 1.0,
        "recall": 0.9708,
        "f1": 0.9852,
        "auc_roc": 0.9993
      },
      "test_opt": {
        "threshold": 0.0847,
        "accuracy": 0.7981,
        "precision": 0.474,
        "recall": 1.0,
        "f1": 0.6432,
        "auc_roc": 0.9993
      },
      "confusion_matrix": [
        [
          616,
          0
        ],
        [
          4,
          133
        ]
      ],
      "confusion_matrix_opt": [
        [
          464,
          152
        ],
        [
          0,
          137
        ]
      ]
    },
    {
      "run": 2,
      "seed": 59,
      "best_iteration": 141,
      "opt_threshold": 0.005,
      "test": {
        "threshold": 0.5,
        "accuracy": 0.9987,
        "precision": 1.0,
        "recall": 0.9919,
        "f1": 0.9959,
        "auc_roc": 1.0
      },
      "test_opt": {
        "threshold": 0.005,
        "accuracy": 0.8274,
        "precision": 0.4862,
        "recall": 1.0,
        "f1": 0.6543,
        "auc_roc": 1.0
      },
      "confusion_matrix": [
        [
          630,
          0
        ],
        [
          1,
          122
        ]
      ],
      "confusion_matrix_opt": [
        [
          500,
          130
        ],
        [
          0,
          123
        ]
      ]
    },
    {
      "run": 3,
      "seed": 76,
      "best_iteration": 16,
      "opt_threshold": 0.2252,
      "test": {
        "threshold": 0.5,
        "accuracy": 0.9907,
        "precision": 1.0,
        "recall": 0.9474,
        "f1": 0.973,
        "auc_roc": 0.9985
      },
      "test_opt": {
        "threshold": 0.2252,
        "accuracy": 0.8181,
        "precision": 0.4926,
        "recall": 1.0,
        "f1": 0.66,
        "auc_roc": 0.9985
      },
      "confusion_matrix": [
        [
          620,
          0
        ],
        [
          7,
          126
        ]
      ],
      "confusion_matrix_opt": [
        [
          483,
          137
        ],
        [
          0,
          133
        ]
      ]
    }
  ],
  "average": {
    "accuracy": 0.9947,
    "precision": 1.0,
    "recall": 0.97,
    "f1": 0.9847,
    "auc_roc": 0.9993
  },
  "std": {
    "accuracy": 0.0033,
    "precision": 0.0,
    "recall": 0.0182,
    "f1": 0.0094,
    "auc_roc": 0.0006
  },
  "average_opt": {
    "accuracy": 0.8145,
    "precision": 0.4843,
    "recall": 1.0,
    "f1": 0.6525,
    "auc_roc": 0.9993
  },
  "std_opt": {
    "accuracy": 0.0122,
    "precision": 0.0077,
    "recall": 0.0,
    "f1": 0.007,
    "auc_roc": 0.0006
  },
  "fileless_generalisation": {
    "threshold": 0.105,
    "accuracy": 1.0,
    "precision": 1.0,
    "recall": 1.0,
    "f1": 1.0,
    "auc_roc": NaN,
    "confusion_matrix": [
      [
        59
      ]
    ]
  }
}